pubchemTools.py
pubchemTool-1.0.9.dist-info/METADATA
pubchemTool-1.0.9.dist-info/WHEEL
pubchemTool-1.0.9.dist-info/top_level.txt
pubchemTool-1.0.9.dist-info/RECORD
